{"filename":"db.json","collections":[{"name":"vendas","data":[{"cliente":"Rodrigo Antunes","produto":"Desodorante","preco":"5.00","qdt":1,"qtd":"2","meta":{"revision":0,"created":1485922816844,"version":0},"$loki":1}],"idIndex":[1],"binaryIndices":{},"constraints":null,"uniqueNames":[],"transforms":{},"objType":"vendas","dirty":false,"cachedIndex":null,"cachedBinaryIndex":null,"cachedData":null,"adaptiveBinaryIndices":true,"transactional":false,"cloneObjects":false,"cloneMethod":"parse-stringify","asyncListeners":false,"disableChangesApi":true,"autoupdate":false,"ttl":null,"maxId":1,"DynamicViews":[],"events":{"insert":[null],"update":[null],"pre-insert":[],"pre-update":[],"close":[],"flushbuffer":[],"error":[],"delete":[null],"warning":[null]},"changes":[]},{"name":"clientes","data":[{"nome":"Rodrigo Antunes","cpf":"15268050737","telefone":"36140716","meta":{"revision":0,"created":1485917739612,"version":0},"$loki":1}],"idIndex":[1],"binaryIndices":{},"constraints":null,"uniqueNames":[],"transforms":{},"objType":"clientes","dirty":false,"cachedIndex":null,"cachedBinaryIndex":null,"cachedData":null,"adaptiveBinaryIndices":true,"transactional":false,"cloneObjects":false,"cloneMethod":"parse-stringify","asyncListeners":false,"disableChangesApi":true,"autoupdate":false,"ttl":null,"maxId":1,"DynamicViews":[],"events":{"insert":[null],"update":[null],"pre-insert":[],"pre-update":[],"close":[],"flushbuffer":[],"error":[],"delete":[null],"warning":[null]},"changes":[]},{"name":"produtos","data":[{"nome":"Desodorante","preco":"5.00","qtd":"3","meta":{"revision":0,"created":1485922805322,"version":0},"$loki":1},{"nome":"Maça","preco":"5,00","qtd":"5","meta":{"revision":1,"created":1485923529404,"version":0,"updated":1485923535073},"$loki":2}],"idIndex":[1,2],"binaryIndices":{},"constraints":null,"uniqueNames":[],"transforms":{},"objType":"produtos","dirty":true,"cachedIndex":null,"cachedBinaryIndex":null,"cachedData":null,"adaptiveBinaryIndices":true,"transactional":false,"cloneObjects":false,"cloneMethod":"parse-stringify","asyncListeners":false,"disableChangesApi":true,"autoupdate":false,"ttl":null,"maxId":2,"DynamicViews":[],"events":{"insert":[null],"update":[null],"pre-insert":[],"pre-update":[],"close":[],"flushbuffer":[],"error":[],"delete":[null],"warning":[null]},"changes":[]}],"databaseVersion":1.1,"engineVersion":1.1,"autosave":false,"autosaveInterval":5000,"autosaveHandle":null,"options":{"serializationMethod":"normal","destructureDelimiter":"$<\n"},"persistenceMethod":"fs","persistenceAdapter":null,"verbose":false,"events":{"init":[null],"loaded":[],"flushChanges":[],"close":[],"changes":[],"warning":[]},"ENV":"NODEJS"}